core/__init__.py
core/calculator.py
core/cpp_bridge.py
core/gpu_accelerator.py
core/math_ops.py
core/performance.py
core/physics_ops.py
core/sequences.py
core/unit_ops.py
interface/__init__.py
interface/ai_interface.py
interface/cli.py
pycalc_pro-2.0.2.dist-info/licenses/LICENSE
pycalc_pro-2.0.2.dist-info/METADATA
pycalc_pro-2.0.2.dist-info/WHEEL
pycalc_pro-2.0.2.dist-info/entry_points.txt
pycalc_pro-2.0.2.dist-info/top_level.txt
pycalc_pro-2.0.2.dist-info/RECORD
