Metadata-Version: 2.4
Name: pycalc-pro
Version: 2.0.2
Summary: PyCalc Pro – High-performance AI math engine with physics, units, and sequence operations.
Author-email: "Li Wen Xiong (李文雄)" <lwx.src@gmail.com>
License-Expression: BSD-3-Clause
Project-URL: Homepage, https://github.com/lw-xiong/pycalc-pro
Classifier: Programming Language :: Python :: 3
Classifier: Programming Language :: Python :: 3.8
Classifier: Operating System :: OS Independent
Classifier: Intended Audience :: Developers
Classifier: Intended Audience :: Science/Research
Classifier: Topic :: Scientific/Engineering :: Artificial Intelligence
Classifier: Topic :: Scientific/Engineering :: Mathematics
Classifier: Topic :: Scientific/Engineering :: Physics
Classifier: Topic :: Software Development :: Libraries :: Python Modules
Requires-Python: >=3.8
License-File: LICENSE
Requires-Dist: numpy
Requires-Dist: numba
Requires-Dist: scipy
Requires-Dist: pint
Provides-Extra: gpu
Requires-Dist: cupy; extra == "gpu"
Dynamic: license-file
